evse_hub/cli/__init__.py
evse_hub/cli/evse_online.py
evse_hub/cli/evse_poll.py
evse_hub/cli/evse_scan.py
evse_hub/cli/runtime.py
evse_hub/cli/status.py
evse_hub/cli/supervisor.py
evse_hub/influx/__init__.py
evse_hub/influx/influx_client.py
evse_hub/influx/influx_writes.py
evse_hub/modbus/__init__.py
evse_hub/modbus/modbus_device.py
evse_hub/modbus/etrel/__init__.py
evse_hub/modbus/etrel/etrel.py
evse_hub/modbus/etrel/modbus_reads.py
evse_hub/modbus/etrel/modbus_writes.py
evse_hub/ops/heartbeat.py
evse_hub/tools/__init__.py
evse_hub/tools/async_tools.py
evse_hub/tools/config.py
evse_hub/tools/device_config.py
evse_hub/tools/wifi.py
evse_hub-0.6.0.dist-info/licenses/LICENSE
evse_hub-0.6.0.dist-info/METADATA
evse_hub-0.6.0.dist-info/WHEEL
evse_hub-0.6.0.dist-info/entry_points.txt
evse_hub-0.6.0.dist-info/top_level.txt
evse_hub-0.6.0.dist-info/RECORD
