Metadata-Version: 2.4
Name: evse-hub
Version: 0.6.0
Summary: Solar monitoring and control daemons
Requires-Python: >=3.11
License-File: LICENSE
Requires-Dist: PyYAML>=6
Requires-Dist: requests>=2
Requires-Dist: pymodbus>=3.11
Requires-Dist: influxdb>=5.3
Requires-Dist: msgpack>=1.0
Requires-Dist: python-dateutil>=2.9
Requires-Dist: pydantic>=2.0
Dynamic: license-file
